pytest_fixture_marker.py
pytest_fixture_marker-0.1.0.dist-info/LICENSE
pytest_fixture_marker-0.1.0.dist-info/METADATA
pytest_fixture_marker-0.1.0.dist-info/WHEEL
pytest_fixture_marker-0.1.0.dist-info/entry_points.txt
pytest_fixture_marker-0.1.0.dist-info/top_level.txt
pytest_fixture_marker-0.1.0.dist-info/RECORD
